README.md
setup.cfg
setup.py
twarc_ids.py
twarc_ids.egg-info/PKG-INFO
twarc_ids.egg-info/SOURCES.txt
twarc_ids.egg-info/dependency_links.txt
twarc_ids.egg-info/entry_points.txt
twarc_ids.egg-info/requires.txt
twarc_ids.egg-info/top_level.txt