Metadata-Version: 2.1
Name: twarc-ids
Version: 0.0.3
Summary: A twarc plugin to read Twitter data and output the tweet ids
Home-page: https://github.com/docnow/twarc-ids
Author: Ed Summers
Author-email: ehs@pobox.com
License: UNKNOWN
Platform: UNKNOWN
Requires-Python: >=3.3
